{
  "image": "-",
  "judul": "5K FUN RUN JAKARTA BARAT",
  "isi_informasi": "Ikuti 5K FUN RUN JAKARTA BARAT yang akan berlangsung pada Minggu, 27 Oktober 2019, dengan lokasi start dan finish di HALL KANTOR WALIKOTA JAKARTA BARAT. Pendaftaran gratis dan peserta akan mendapatkan T-shirt. Persyaratan pendaftaran berbeda untuk kategori umum, pelajar, dan ASN Pemda DKI Jakarta. Pendaftaran dibuka dari 25 September hingga 15 Oktober 2019, setiap hari Senin hingga Jumat, pukul 08.00 WIB hingga 16.00 WIB. Terdapat hadiah untuk juara di masing-masing kategori.",
  "benefit_peserta": [
    "Pendaftaran gratis",
    "Mendapatkan T-shirt",
    "Hadiah untuk juara"
  ],
  "lokasi": "HALL KANTOR WALIKOTA JAKARTA BARAT",
  "kota": "Jakarta Barat",
  "tanggal_event": "2019-10-27",
  "kontak_event": {
    "WhatsApp": "0812 119 911",
    "Email": "kontak@indonesiamarathon.com",
    "Website": "www.indonesiamarathon.com"
  },
  "biaya_registrasi": "Gratis",
  "kategori": [
    "5K"
  ],
  "jenis_event": "fun run"
}