{
  "image": "-",
  "judul": "Beach Run Tropical Sunset",
  "isi_informasi": "Ikuti Beach Run Tropical Sunset di Pantai Lagoon, Ancol Jakarta pada 27 April 2019. Acara ini akan berlangsung dari pukul 14.30 hingga 18.00. Peserta akan mendapatkan medali finisher, kaos, dan nomor dada. Terdapat juga hadiah menarik yang bisa dimenangkan.",
  "benefit_peserta": [
    "Medali finisher",
    "Kaos",
    "Nomor dada",
    "Kesempatan memenangkan hadiah"
  ],
  "lokasi": "Pantai Lagoon, Ancol Jakarta",
  "kota": "Jakarta",
  "tanggal_event": "2019-04-27",
  "kontak_event": {
    "WhatsApp": "081296376930",
    "Email": "kontak@indonesiamarathon.com",
    "Website": "www.indonesiamarathon.com"
  },
  "biaya_registrasi": "Rp 125.000",
  "kategori": [
    "Fun Run"
  ],
  "jenis_event": "fun run"
}