{
  "image": "-",
  "judul": "FUN RUN WALK KONI KENDAL 2019",
  "isi_informasi": "Event lari ini akan diadakan pada 20 Oktober 2019 di Stadion Utama Kebondalem Kendal, Jawa Tengah. Terdapat kategori 3K Family Run, 5K, dan 10K. Pendaftaran dapat dilakukan secara online melalui link yang disediakan dan konfirmasi melalui WhatsApp.",
  "benefit_peserta": [
    "Kesempatan berolahraga bersama keluarga",
    "Mendapatkan pengalaman berlari di event resmi",
    "Berpartisipasi dalam komunitas lari"
  ],
  "lokasi": "Stadion Utama Kebondalem Kendal, Jawa Tengah",
  "kota": "Kendal",
  "tanggal_event": "2019-10-20",
  "kontak_event": {
    "WhatsApp": "0895415469222",
    "Email": "kontak@indonesiamarathon.com",
    "Website": "www.indonesiamarathon.com"
  },
  "biaya_registrasi": "Tidak tercantum",
  "kategori": [
    "3K",
    "5K",
    "10K"
  ],
  "jenis_event": "fun run"
}