{
  "image": "-",
  "judul": "IPDN RUN 2019",
  "isi_informasi": "Event lari IPDN RUN 2019 akan diselenggarakan pada 17 Maret 2019 dengan kategori 5K. Untuk informasi lebih lanjut dan pendaftaran, kunjungi situs resmi.",
  "benefit_peserta": [
    "Kesempatan berolahraga",
    "Meningkatkan kesehatan",
    "Bertemu komunitas lari"
  ],
  "lokasi": "Ksatriaan IPDN Jatinangor",
  "kota": "Sumedang",
  "tanggal_event": "2019-03-17",
  "kontak_event": {
    "WhatsApp": "0812 119 911",
    "Email": "kontak@indonesiamarathon.com",
    "Website": "www.indonesiamarathon.com"
  },
  "biaya_registrasi": "Tidak tercantum",
  "kategori": [
    "5K"
  ],
  "jenis_event": "road run"
}