{
  "image": "-",
  "judul": "Kimia Farma Trail Run",
  "isi_informasi": "Acara lari trail sejauh 8 km ini diselenggarakan oleh Kimia Farma Balikpapan pada 14 April 2019, mulai pukul 07:00. Start dan finish di Kimia Farma, Jl Soekarno Hatta KM 8. Biaya pendaftaran sebesar Rp 80.000,- mencakup kaos finisher untuk 50 penyelesaian tercepat, medali, hidrasi, makanan ringan, doorprize, dan hadiah untuk pemenang. Pendaftaran dilakukan di Kimia Farma Klandasan, Jl Jend. Sudirman no 2-3, Klandasan, dari pukul 08:00 hingga 24:00. 100 pendaftar pertama akan mendapatkan dua voucher eksklusif dari Kimia Farma.",
  "benefit_peserta": [
    "Kaos finisher untuk 50 penyelesaian tercepat",
    "Medali",
    "Hidrasi",
    "Makanan ringan",
    "Doorprize",
    "Hadiah untuk pemenang",
    "Dua voucher eksklusif dari Kimia Farma"
  ],
  "lokasi": "Kimia Farma Jl Soekarno Hatta KM 8, Balikpapan",
  "kota": "Balikpapan",
  "tanggal_event": "2019-04-14",
  "kontak_event": {
    "WhatsApp": "0812 119 911",
    "Email": "kontak@indonesiamarathon.com",
    "Website": "www.indonesiamarathon.com"
  },
  "biaya_registrasi": "Rp 80.000,-",
  "kategori": [
    "8K"
  ],
  "jenis_event": "trail run"
}