{
  "image": "-",
  "judul": "Lari Bareng GTMAN",
  "isi_informasi": "Ayo bergabung dalam acara #LariBarengGTMan di GBK Senayan pada 17 Oktober 2019! Acara ini berupa jogging santai bersama teman-teman dan dilengkapi dengan permainan berhadiah serta face painting. Pendaftaran gratis dan terbuka untuk umum, dengan hadiah menarik bagi 20 pendaftar pertama.",
  "benefit_peserta": [
    "Refreshment pack",
    "Face painting gratis",
    "Gelang glow in the dark",
    "Kesempatan memenangkan voucher GT Man"
  ],
  "lokasi": "GBK Senayan, Jakarta",
  "kota": "Jakarta",
  "tanggal_event": "2019-10-17",
  "kontak_event": {
    "Instagram": [
      "@gtman_official"
    ],
    "WhatsApp": "0812 119 911",
    "Email": "kontak@indonesiamarathon.com",
    "Website": "www.indonesiamarathon.com"
  },
  "biaya_registrasi": "Gratis",
  "kategori": [
    "3K Fun Run"
  ],
  "jenis_event": "fun run"
}