{
  "image": "-",
  "judul": "Run for Hope 2019",
  "isi_informasi": "Run for Hope 2019 adalah acara lari yang diselenggarakan oleh Siloam Hospital untuk merayakan HUT MRCCC yang ketujuh dan World Cancer Day. Tujuan acara ini adalah mengumpulkan dana untuk pengobatan pasien kanker di MRCCC, meningkatkan kesadaran masyarakat tentang kanker dan kesehatan, serta pentingnya berolahraga, dan membangun hubungan baik antara pasien, dokter, dan staf rumah sakit.",
  "benefit_peserta": [
    "Mengumpulkan dana untuk pasien kanker",
    "Meningkatkan kesadaran tentang kanker dan kesehatan",
    "Mendorong pentingnya berolahraga",
    "Menjalin hubungan baik antara pasien dan tenaga medis"
  ],
  "lokasi": "PLAZA SEMANGGI, Jakarta",
  "kota": "Jakarta",
  "tanggal_event": "2019-02-10",
  "kontak_event": {
    "WhatsApp": "0812 119 911",
    "Email": "kontak@indonesiamarathon.com",
    "Website": "www.indonesiamarathon.com"
  },
  "biaya_registrasi": "Tidak tercantum",
  "kategori": [
    "5K"
  ],
  "jenis_event": "road run"
}