{
  "image": "-",
  "judul": "Sleman Temple Run 2019",
  "isi_informasi": "Sleman Temple Run 2019 akan berlangsung pada 14 Juli 2019, merupakan penyelenggaraan yang kelima kalinya. Terdapat kategori lari 7K, 13K, dan 25K.",
  "benefit_peserta": [
    "Kesempatan berlari di lokasi bersejarah",
    "Mendapatkan pengalaman berlari yang unik",
    "Berpartisipasi dalam komunitas lari"
  ],
  "lokasi": "Candi Banyunibo, Sleman, Yogyakarta",
  "kota": "Sleman",
  "tanggal_event": "2019-07-14",
  "kontak_event": {
    "WhatsApp": "+6282225133391",
    "Email": "slemantemplerun.jogja@gmail.com",
    "Website": "www.indonesiamarathon.com"
  },
  "biaya_registrasi": "Tidak tercantum",
  "kategori": [
    "7K",
    "13K",
    "25K"
  ],
  "jenis_event": "road run"
}