{
  "image": "-",
  "judul": "Fun Run Indomaret 2023",
  "isi_informasi": "Tiket untuk event Fun Run Indomaret 2023 dijual seharga Rp. 75.000,- dan dapat dibeli di semua toko Indomaret serta Klik Indomaret. Peserta harus membawa struk pembelian untuk ditukarkan dengan tiket, jersey, topi, dan goodie bag. Peserta diharuskan dalam kondisi sehat dan tidak memiliki riwayat penyakit. Selama acara, peserta wajib mengenakan jersey yang disediakan dan mengikuti rute yang telah ditentukan. Data diri lengkap harus diisi pada Kupon Undian yang terdapat di tiket dan dikumpulkan di dropbox.",
  "benefit_peserta": [
    "Tiket, jersey, topi, dan goodie bag",
    "Kesempatan mengikuti undian"
  ],
  "lokasi": "Tidak tercantum",
  "kota": "Palembang",
  "tanggal_event": "2023-12-01",
  "kontak_event": {
    "WhatsApp": "0812 119 911",
    "Email": "kontak@indonesiamarathon.com",
    "Website": "www.indonesiamarathon.com"
  },
  "biaya_registrasi": "Rp. 75.000,-",
  "kategori": [
    "5K"
  ],
  "jenis_event": "fun run"
}