{
  "image": "-",
  "judul": "Independence Day Charity Fun Run \"Merdeka untuk Hutan\"",
  "isi_informasi": "Ikuti acara lari sejauh 7,8 km yang diselenggarakan oleh Hutan Itu Indonesia, Forestisme Bandung, dan Kecerun pada 17 Agustus 2023 di Kofu Coffee, Bandung. Acara ini bertujuan mendukung Adopsi Hutan di Gunung Masigit Kareumbi. Biaya registrasi sebesar 25 ribu rupiah untuk donasi, dengan kesempatan mendapatkan doorprize dan menikmati refreshment gratis. Ayo tunjukkan semangat kemerdekaan dengan kostum unik bertema kemerdekaan atau hutan!",
  "benefit_peserta": [
    "Kesempatan mendapatkan doorprize",
    "Refreshment gratis",
    "Mendukung Adopsi Hutan"
  ],
  "lokasi": "Kofu Coffee, Jl. Cisangkuy No.58 Bandung",
  "kota": "Bandung",
  "tanggal_event": "2023-08-17",
  "kontak_event": {
    "WhatsApp": "0812 119 911",
    "Email": "kontak@indonesiamarathon.com",
    "Website": "www.indonesiamarathon.com"
  },
  "biaya_registrasi": "25.000",
  "kategori": [
    "5K"
  ],
  "jenis_event": "fun run"
}