{
  "image": "Aryaduta_Family_Fun_Run_2025_2025-07-26.jpg",
  "judul": "Aryaduta Family Fun Run 2025",
  "isi_informasi": "Aryaduta Family Fun Run 2025 adalah acara lari keluarga yang penuh keceriaan, berlangsung pada 26 Juli 2025 di Pantai Jerman, Badung, Bali. Setiap langkah dalam acara ini bertujuan untuk mempererat kebersamaan. Peserta akan mendapatkan jersey, medali finisher, nomor BIB, dan goodie bag.",
  "benefit_peserta": [
    "Jersey",
    "Finisher Medal",
    "BIB Number",
    "Goodie Bag"
  ],
  "lokasi": "Pantai Jerman, Badung, Bali",
  "kota": "Badung",
  "tanggal_event": "2025-07-26",
  "kontak_event": {
    "Instagram": [
      "@aryadutafamilyfunrun"
    ],
    "WhatsApp": "+62 812 5555 9343"
  },
  "biaya_registrasi": {
    "3K": "IDR 150.000"
  },
  "kategori": [
    "3K"
  ],
  "jenis_event": "fun run"
}