{
  "image": "JETE_RUN_Goes_to_Bali_2025_2025-07-06.jpeg",
  "judul": "JETE RUN Goes to Bali 2025",
  "isi_informasi": "JETE Run Goes to Bali 2025 akan berlangsung pada 6 Juli 2025, menggabungkan olahraga dengan keindahan alam Bali. Peserta akan berlari di bawah sinar matahari pagi sambil menikmati suasana tropis. Event ini merayakan energi, komunitas, dan gaya hidup aktif dengan berbagai kegiatan seperti pemanasan sebelum lomba dan pesta setelah lomba.",
  "benefit_peserta": [
    "Jersey",
    "Medali",
    "BIB Number",
    "Race Belt",
    "Sponsor Kit",
    "Refreshment"
  ],
  "lokasi": "Taman Inspirasi Muntig Siokan, Denpasar, Bali",
  "kota": "Denpasar",
  "tanggal_event": "2025-07-06",
  "kontak_event": {
    "Instagram": [
      "@jeterunid",
      "@jeteindonesia"
    ],
    "WhatsApp": "+62 852-1753-3392"
  },
  "biaya_registrasi": {
    "5K": "IDR 149.900",
    "5K + OpenTune": "IDR 399.800",
    "5K + OpenNeo": "IDR 399.800",
    "5K + OpenStyle": "IDR 499.900",
    "5K + OpenPulse": "IDR 599.900",
    "5K + OpenEar 2": "IDR 949.800",
    "5K + OpenFast": "IDR 1.049.800"
  },
  "kategori": [
    "5K"
  ],
  "jenis_event": "road run"
}