{
  "image": "Maratua_Run_2025_2025-02-15.png",
  "judul": "Maratua Run 2025",
  "isi_informasi": "Maratua Run 2025 diadakan untuk merayakan HUT ke-68 Provinsi Kalimantan Timur. Acara ini bertujuan untuk mempromosikan keindahan Pulau Maratua dan meningkatkan kesadaran akan pentingnya olahraga. Dengan rute yang menawarkan pemandangan tropis yang menakjubkan, event ini cocok untuk pelari profesional maupun pemula. Peserta akan mendapatkan jersey eksklusif, bib berteknologi chip, medali finisher, string bag, asuransi, e-racebook, e-certificate, dan layanan photo tagging. Biaya pendaftaran juga mencakup transportasi speed boat dari Dermaga Wisata Sanggam Tanjung Redeb ke Pulau Maratua.",
  "benefit_peserta": [
    "Jersey eksklusif",
    "Bib berteknologi chip",
    "Medali finisher",
    "String bag",
    "Perlindungan asuransi",
    "E-racebook",
    "E-certificate",
    "Layanan photo tagging",
    "Transportasi speed boat pulang-pergi"
  ],
  "lokasi": "Kantor Camat Maratua, Kabupaten Berau, Kalimantan Timur",
  "kota": "Berau",
  "tanggal_event": "2025-02-15",
  "kontak_event": {
    "Instagram": [
      "@maratua.run",
      "@im_roadrunner"
    ],
    "WhatsApp": "0822-5807-5606"
  },
  "biaya_registrasi": {
    "5K Lokal": "IDR 250.000",
    "10K Lokal": "IDR 300.000",
    "5K Close/Umum": "IDR 900.000",
    "10K Close/Umum": "IDR 1.100.000",
    "10K Open/Foreign": "IDR 1.700.000"
  },
  "kategori": [
    "5K",
    "10K"
  ],
  "jenis_event": "road run"
}