{
  "image": "PurnawiRun_2025_2025-08-24.png",
  "judul": "PurnawiRun 2025",
  "isi_informasi": "PurnawiRun adalah maraton yang diadakan oleh OSIS SMA Negeri 2 Klaten di Candi Sojiwan, sebuah situs bersejarah yang dikelilingi alam hijau. Setelah sukses tahun lalu, PurnawiRun 2025 menawarkan berbagai kegiatan menarik dan penampilan bintang tamu. Acara ini bertujuan untuk meningkatkan kemampuan pelari, mempererat persaudaraan, dan menumbuhkan semangat kebersamaan. Daftarkan diri Anda untuk mengikuti perlombaan pada 24 Agustus 2025.",
  "benefit_peserta": [
    "Race Jersey",
    "Finisher Medal",
    "Special Podium Medal",
    "BIB Number",
    "Kartu Perdana Smartfren",
    "Totebag",
    "Water Station & Pos Refreshment",
    "Podium 1 – 2 – 3 Umum & Pelajar (Putra & Putri)",
    "Podium 1 atlet (Putra & Putri)",
    "Tiket masuk Candi Sojiwan",
    "Doorprize",
    "Special Piagam Podium",
    "Entertainment",
    "Mini Talkshow",
    "Dokumentasi"
  ],
  "lokasi": "Candi Sojiwan, Klaten, Jawa Tengah",
  "kota": "Klaten",
  "tanggal_event": "2025-08-24",
  "kontak_event": {
    "Instagram": [
      "@purnawirun"
    ],
    "WhatsApp": "0857 4139 2649"
  },
  "biaya_registrasi": {
    "6K": "IDR 200.000",
    "6K (Kolektif 3 /Orang)": "IDR 175.000",
    "6K (Kolektif 5 /Orang)": "IDR 150.000"
  },
  "kategori": [
    "6K"
  ],
  "jenis_event": "road run"
}