{
  "image": "SAC_Fun_Run_Sumatera_-_Medan_2024-10-13.png",
  "judul": "SAC Fun Run Sumatera - Medan",
  "isi_informasi": "SAC Indonesia Fun Run adalah program lari jalanan yang diadakan oleh Student Athletics Championships (SAC) Indonesia, hasil kolaborasi DBL Indonesia dan PB PASI. Acara ini bertujuan untuk mempopulerkan olahraga atletik dan akan diadakan di beberapa kota, termasuk Medan, pada 13 Oktober 2024.",
  "benefit_peserta": [
    "Mengenal ragam lomba atletik",
    "Kesempatan berpartisipasi dalam event lari"
  ],
  "lokasi": "Medan, Sumatera Utara",
  "kota": "Medan",
  "tanggal_event": "2024-10-13",
  "kontak_event": {
    "Instagram": [],
    "WhatsApp": "0823 3786 7209"
  },
  "biaya_registrasi": {
    "5K": "IDR 100.000"
  },
  "kategori": [
    "5K"
  ],
  "jenis_event": "road run"
}