{
  "image": "TGM_Fun_Run_2024_2024-11-03.png",
  "judul": "TGM Fun Run 2024",
  "isi_informasi": "Ikuti TGM Fun Run 5 KM untuk merayakan peluncuran resmi Tirtagangga Gita Maya Group dan mulai gaya hidup sehat. Acara ini dijadwalkan ulang dari 8 September 2024 menjadi 3 November 2024.",
  "benefit_peserta": [
    "Mendukung gaya hidup sehat",
    "Kesempatan berlari bersama komunitas"
  ],
  "lokasi": "Alas Daun, Bandung, Jawa Barat",
  "kota": "Bandung",
  "tanggal_event": "2024-11-03",
  "kontak_event": {
    "Instagram": [],
    "WhatsApp": "0823 3786 7209"
  },
  "biaya_registrasi": {
    "5K": "IDR 180.000"
  },
  "kategori": [
    "5K"
  ],
  "jenis_event": "fun run"
}